audioio/__init__.py
audioio/audioconverter.py
audioio/audioloader.py
audioio/audiomarkers.py
audioio/audiometadata.py
audioio/audiomodules.py
audioio/audiotools.py
audioio/audiowriter.py
audioio/bufferedarray.py
audioio/fixtimestamps.py
audioio/playaudio.py
audioio/riffmetadata.py
audioio/version.py
audioio-2.7.0.dist-info/licenses/LICENSE
audioio-2.7.0.dist-info/METADATA
audioio-2.7.0.dist-info/WHEEL
audioio-2.7.0.dist-info/entry_points.txt
audioio-2.7.0.dist-info/top_level.txt
audioio-2.7.0.dist-info/RECORD
