Metadata-Version: 2.4
Name: audioio
Version: 2.7.0
Summary: Platform independent interfacing of numpy arrays of floats with audio files and devices for scientific data analysis.
Author-email: Jan Benda <jan.benda@uni-tuebingen.de>
Maintainer-email: Jan Benda <jan.benda@uni-tuebingen.de>
License:                     GNU GENERAL PUBLIC LICENSE
Project-URL: Repository, https://github.com/bendalab/audioio
Project-URL: Documentation, https://bendalab.github.io/audioio
Classifier: Development Status :: 5 - Production/Stable
Classifier: Environment :: Console
Classifier: Intended Audience :: Science/Research
Classifier: License :: OSI Approved :: GNU General Public License v3 (GPLv3)
Classifier: Natural Language :: English
Classifier: Programming Language :: Python :: 3
Classifier: Programming Language :: Python :: 3.8
Classifier: Programming Language :: Python :: 3.12
Classifier: Operating System :: OS Independent
Classifier: Topic :: Multimedia :: Sound/Audio
Classifier: Topic :: Multimedia :: Sound/Audio :: Analysis
Classifier: Topic :: Multimedia :: Sound/Audio :: Conversion
Classifier: Topic :: Scientific/Engineering
Classifier: Topic :: Software Development :: Libraries :: Python Modules
Requires-Python: >=3.6
License-File: LICENSE
Requires-Dist: numpy
Requires-Dist: scipy
Dynamic: license-file
